LICENSE
MANIFEST.in
README.rst
setup.py
docs/CONTRIBUTING.rst
docs/Makefile
docs/README.rst
docs/conf.py
docs/contributors.rst
docs/details.rst
docs/docstring_docs.rst
docs/index.rst
docs/make.bat
docs/usefullinks.rst
docs/images/boxplot_lex_nyt_cnn_npr_msnbc.png
docs/images/vocd.png
lexicalrichness/__init__.py
lexicalrichness/lexicalrichness.py
lexicalrichness.egg-info/PKG-INFO
lexicalrichness.egg-info/SOURCES.txt
lexicalrichness.egg-info/dependency_links.txt
lexicalrichness.egg-info/requires.txt
lexicalrichness.egg-info/top_level.txt
tests/__init__.py
tests/test_lexicalrichness.py