Metadata-Version: 2.1
Name: lexicalrichness
Version: 0.5.0
Summary: A small module to compute textual lexical richness (aka lexical diversity).
Home-page: https://github.com/LSYS/lexicalrichness
Download-URL: https://github.com/LSYS/LexicalRichness/archive/refs/tags/v0.5.0.tar.gz
Author: Lucas Shen YS
Author-email: lucas@lucasshen.com
License: MIT license
Keywords: lexical diversity,lexical richness,vocabulary diversity,lexical density,lexical,nlp,data science,natural language processing,information retrieval,data mining,natural langauge,lexical analysis,api,lexical analyzer,linguistic analysis,statistics
Classifier: Development Status :: 2 - Pre-Alpha
Classifier: Intended Audience :: Developers
Classifier: License :: OSI Approved :: MIT License
Classifier: Natural Language :: English
Classifier: Programming Language :: Python :: 3
Classifier: Programming Language :: Python :: 3.6
Classifier: Programming Language :: Python :: 3.7
Classifier: Programming Language :: Python :: 3.8
Classifier: Programming Language :: Python :: 3.9
Classifier: Programming Language :: Python :: 3.10
License-File: LICENSE
